share_pro.py
share_pro-0.0.5.dist-info/LICENSE
share_pro-0.0.5.dist-info/METADATA
share_pro-0.0.5.dist-info/WHEEL
share_pro-0.0.5.dist-info/entry_points.txt
share_pro-0.0.5.dist-info/top_level.txt
share_pro-0.0.5.dist-info/RECORD
