Metadata-Version: 2.1
Name: share-pro
Version: 0.0.5
Summary: Share your computer files to android over wifi.
Home-page: https://github.com/jakbin/share-pro
Author: jakbin
License: MIT License
Keywords: share-pro,wifi-file-transfer,file-tranfer
Platform: any
Classifier: Development Status :: 4 - Beta
Classifier: License :: OSI Approved :: MIT License
Classifier: Operating System :: OS Independent
Classifier: Programming Language :: Python
Classifier: Programming Language :: Python :: 3
License-File: LICENSE
Requires-Dist: qrcode
